{
  "source": "bps_webapi",
  "source_no": 47,
  "source_nama_ramah": "Wisatawan Nusantara",
  "source_tabel_db": "usecase_ekonomi.ekonomi_wisatawan_nusantara",
  "source_url": "https://www.bps.go.id/id/statistics-table/2/MjIwMSMy/jumlah-perjalanan-wisatawan-nusantara-menurut-provinsi-tujuan--perjalanan-.html",
  "source_judul_resmi_tabel": "Jumlah Perjalanan Wisatawan Nusantara Menurut Provinsi Tujuan (Perjalanan), 2026",
  "api_info": {
    "var_id": "2201",
    "target_year_from_title": "2026",
    "selected_th_id": "126",
    "selected_th_year": "2026",
    "selected_th_reason": "match_target_year",
    "available_years": [
      {
        "th_id": 126,
        "th": "2026"
      },
      {
        "th_id": 125,
        "th": "2025"
      },
      {
        "th_id": 124,
        "th": "2024"
      },
      {
        "th_id": 123,
        "th": "2023"
      },
      {
        "th_id": 122,
        "th": "2022"
      },
      {
        "th_id": 121,
        "th": "2021"
      },
      {
        "th_id": 120,
        "th": "2020"
      },
      {
        "th_id": 119,
        "th": "2019"
      }
    ]
  },
  "title_score": 1.0,
  "chosen_bps_label": "Jumlah Perjalanan Wisatawan Nusantara Menurut Provinsi Tujuan",
  "meta": {
    "var_id": "2201",
    "variabel": "Jumlah Perjalanan Wisatawan Nusantara Menurut Provinsi Tujuan",
    "unit": "Perjalanan",
    "subject": "Pariwisata",
    "note": "<p><br /></p><p><br /></p><p><br /></p><p><br /></p><p><br /></p><p><br /></p><p><br /></p><p><br /></p><p><br /></p><p><br /></p><p><br /></p><p><br /></p><p><br /></p><p><br /></p><p><br /></p><p>Sumber: Badan Pusat Statistik<br /></p><p><br /></p><p><br /></p><p><br /></p><p><br /></p><p><br /></p><p><br /></p><p><br /></p><p><br /></p><p><br /></p><p><br /></p><p><br /></p><p><br /></p><p><br /></p><p><br /></p><p><br /></p><p><br /></p><p><br /></p><p><br /></p><p><br /></p><p><br /></p><p><br /></p><p><br /></p><p><br /></p><p><br /></p><p><br /></p><p><br /></p><p><br /></p><p><br /></p><p><br /></p><p><br /></p><p><br /></p>"
  },
  "data": {
    "status": "OK",
    "data-availability": "available",
    "last_update": "2026-06-04 09:37:31",
    "subject": [
      {
        "val": 561,
        "label": "Pariwisata"
      }
    ],
    "var": [
      {
        "val": 2201,
        "label": "Jumlah Perjalanan Wisatawan Nusantara Menurut Provinsi Tujuan",
        "unit": "Perjalanan",
        "subj": "Pariwisata",
        "def": "-",
        "decimal": 0,
        "note": "<p><br /></p><p><br /></p><p><br /></p><p><br /></p><p><br /></p><p><br /></p><p><br /></p><p><br /></p><p><br /></p><p><br /></p><p><br /></p><p><br /></p><p><br /></p><p><br /></p><p><br /></p><p>Sumber: Badan Pusat Statistik<br /></p><p><br /></p><p><br /></p><p><br /></p><p><br /></p><p><br /></p><p><br /></p><p><br /></p><p><br /></p><p><br /></p><p><br /></p><p><br /></p><p><br /></p><p><br /></p><p><br /></p><p><br /></p><p><br /></p><p><br /></p><p><br /></p><p><br /></p><p><br /></p><p><br /></p><p><br /></p><p><br /></p><p><br /></p><p><br /></p><p><br /></p><p><br /></p><p><br /></p><p><br /></p><p><br /></p><p><br /></p>"
      }
    ],
    "turvar": [
      {
        "val": "0",
        "label": "Tidak ada"
      }
    ],
    "labelvervar": "38 Provinsi",
    "vervar": [
      {
        "val": 1100,
        "label": "ACEH"
      },
      {
        "val": 1200,
        "label": "SUMATERA UTARA"
      },
      {
        "val": 1300,
        "label": "SUMATERA BARAT"
      },
      {
        "val": 1400,
        "label": "RIAU"
      },
      {
        "val": 1500,
        "label": "JAMBI"
      },
      {
        "val": 1600,
        "label": "SUMATERA SELATAN"
      },
      {
        "val": 1700,
        "label": "BENGKULU"
      },
      {
        "val": 1800,
        "label": "LAMPUNG"
      },
      {
        "val": 1900,
        "label": "KEP. BANGKA BELITUNG"
      },
      {
        "val": 2100,
        "label": "KEP. RIAU"
      },
      {
        "val": 3100,
        "label": "DKI JAKARTA"
      },
      {
        "val": 3200,
        "label": "JAWA BARAT"
      },
      {
        "val": 3300,
        "label": "JAWA TENGAH"
      },
      {
        "val": 3400,
        "label": "DI YOGYAKARTA"
      },
      {
        "val": 3500,
        "label": "JAWA TIMUR"
      },
      {
        "val": 3600,
        "label": "BANTEN"
      },
      {
        "val": 5100,
        "label": "BALI"
      },
      {
        "val": 5200,
        "label": "NUSA TENGGARA BARAT"
      },
      {
        "val": 5300,
        "label": "NUSA TENGGARA TIMUR"
      },
      {
        "val": 6100,
        "label": "KALIMANTAN BARAT"
      },
      {
        "val": 6200,
        "label": "KALIMANTAN TENGAH"
      },
      {
        "val": 6300,
        "label": "KALIMANTAN SELATAN"
      },
      {
        "val": 6400,
        "label": "KALIMANTAN TIMUR"
      },
      {
        "val": 6500,
        "label": "KALIMANTAN UTARA"
      },
      {
        "val": 7100,
        "label": "SULAWESI UTARA"
      },
      {
        "val": 7200,
        "label": "SULAWESI TENGAH"
      },
      {
        "val": 7300,
        "label": "SULAWESI SELATAN"
      },
      {
        "val": 7400,
        "label": "SULAWESI TENGGARA"
      },
      {
        "val": 7500,
        "label": "GORONTALO"
      },
      {
        "val": 7600,
        "label": "SULAWESI BARAT"
      },
      {
        "val": 8100,
        "label": "MALUKU"
      },
      {
        "val": 8200,
        "label": "MALUKU UTARA"
      },
      {
        "val": 9100,
        "label": "PAPUA BARAT"
      },
      {
        "val": 9200,
        "label": "PAPUA BARAT DAYA"
      },
      {
        "val": 9400,
        "label": "PAPUA"
      },
      {
        "val": 9500,
        "label": "PAPUA SELATAN"
      },
      {
        "val": 9600,
        "label": "PAPUA TENGAH"
      },
      {
        "val": 9700,
        "label": "PAPUA PEGUNUNGAN"
      },
      {
        "val": 9999,
        "label": "INDONESIA"
      }
    ],
    "tahun": [
      {
        "val": 126,
        "label": "2026"
      }
    ],
    "turtahun": [
      {
        "val": 1,
        "label": "Januari"
      },
      {
        "val": 2,
        "label": "Februari"
      },
      {
        "val": 3,
        "label": "Maret"
      },
      {
        "val": 4,
        "label": "April"
      },
      {
        "val": 5,
        "label": "Mei"
      },
      {
        "val": 6,
        "label": "Juni"
      },
      {
        "val": 7,
        "label": "Juli"
      },
      {
        "val": 8,
        "label": "Agustus"
      },
      {
        "val": 9,
        "label": "September"
      },
      {
        "val": 10,
        "label": "Oktober"
      },
      {
        "val": 11,
        "label": "November"
      },
      {
        "val": 12,
        "label": "Desember"
      },
      {
        "val": 13,
        "label": "Tahunan"
      }
    ],
    "datacontent": {
      "5300220101261": 920409,
      "9500220101264": 26834,
      "7100220101261": 1232868,
      "1900220101263": 467604,
      "6400220101261": 1375871,
      "8200220101263": 366211,
      "7400220101264": 1004213,
      "1900220101264": 371039,
      "3100220101261": 8710629,
      "7300220101261": 4096980,
      "9700220101264": 55216,
      "9600220101262": 65216,
      "6200220101263": 1213887,
      "1400220101262": 1889747,
      "1100220101263": 2263684,
      "3300220101261": 11953858,
      "3200220101264": 17397606,
      "9700220101262": 57579,
      "8200220101264": 311277,
      "3200220101261": 18382219,
      "6200220101264": 930238,
      "3300220101263": 20007121,
      "8100220101261": 343252,
      "1200220101263": 6429013,
      "9500220101261": 31387,
      "9100220101261": 82101,
      "1100220101262": 1469012,
      "5100220101262": 1992887,
      "9999220101263": 126339846,
      "2100220101261": 379169,
      "2100220101263": 470304,
      "5100220101264": 2248855,
      "3400220101263": 3763897,
      "7600220101262": 330162,
      "9999220101264": 97546288,
      "1200220101264": 4706748,
      "7600220101264": 359215,
      "6400220101264": 1179463,
      "7300220101263": 4346194,
      "6300220101264": 1471987,
      "7500220101262": 415630,
      "1200220101262": 4427868,
      "1900220101261": 386526,
      "1400220101264": 1953412,
      "7400220101262": 1012170,
      "1300220101261": 1690551,
      "1300220101262": 1687690,
      "1800220101264": 1849845,
      "1500220101261": 923147,
      "5100220101263": 2295374,
      "7200220101263": 1167765,
      "3200220101263": 22482742,
      "5300220101264": 807516,
      "7100220101262": 1052830,
      "6100220101261": 1245754,
      "6200220101262": 867864,
      "1600220101262": 1860610,
      "3500220101262": 16128443,
      "3400220101264": 3592783,
      "3600220101264": 5441191,
      "5200220101261": 1194306,
      "8100220101264": 309614,
      "6100220101264": 1178429,
      "6400220101263": 1594585,
      "1300220101264": 1886972,
      "6200220101261": 999644,
      "8200220101262": 270587,
      "1400220101263": 2555647,
      "2100220101262": 342470,
      "7100220101264": 1213247,
      "7200220101262": 880248,
      "7600220101261": 411096,
      "9200220101262": 132948,
      "3600220101261": 5164560,
      "1700220101263": 809588,
      "3400220101262": 3087623,
      "3400220101261": 3530043,
      "6100220101262": 1137134,
      "7200220101261": 1042351,
      "2100220101264": 359858,
      "9200220101264": 139389,
      "1600220101261": 2093121,
      "5200220101262": 1034930,
      "9100220101262": 70375,
      "3200220101262": 15670287,
      "1800220101263": 2910547,
      "6100220101263": 1568597,
      "6500220101261": 152246,
      "1800220101262": 1937069,
      "5300220101263": 867965,
      "1100220101264": 1618520,
      "8200220101261": 343728,
      "7500220101261": 473246,
      "9400220101263": 260842,
      "1700220101262": 509672,
      "3100220101263": 8620025,
      "6500220101263": 163095,
      "1800220101261": 2276319,
      "9999220101261": 102038288,
      "7200220101264": 957947,
      "3500220101263": 20776964,
      "7300220101262": 3311374,
      "9400220101261": 285708,
      "8100220101263": 383545,
      "5200220101264": 1205922,
      "1600220101263": 2779335,
      "6500220101262": 125693,
      "3100220101262": 8122096,
      "9100220101264": 69166,
      "6400220101262": 1129165,
      "3100220101264": 8415432,
      "3600220101262": 4943547,
      "9100220101263": 81180,
      "9200220101263": 152885,
      "9600220101261": 96813,
      "5200220101263": 1393460,
      "3300220101264": 13222400,
      "9400220101264": 228929,
      "7500220101263": 572637,
      "6500220101264": 137309,
      "3500220101264": 15401119,
      "9600220101263": 71228,
      "7300220101264": 3566908,
      "6300220101262": 1386419,
      "9700220101263": 64510,
      "1700220101264": 550559,
      "9700220101261": 83132,
      "6300220101263": 1888664,
      "8100220101262": 289124,
      "1400220101261": 2060155,
      "1100220101261": 1515377,
      "7600220101263": 439708,
      "9200220101261": 168869,
      "9400220101262": 228431,
      "1200220101261": 5203604,
      "3300220101262": 11306263,
      "6300220101261": 1633168,
      "7100220101263": 1295077,
      "1500220101263": 1174217,
      "1900220101262": 360809,
      "7400220101263": 1248345,
      "7500220101264": 454687,
      "9600220101264": 64350,
      "1600220101264": 2003241,
      "1500220101264": 854852,
      "9999220101262": 91135258,
      "5300220101262": 758334,
      "1700220101261": 624011,
      "1300220101263": 2796192,
      "3600220101263": 6565677,
      "1500220101262": 818339,
      "5100220101261": 2170938,
      "7400220101261": 1182081,
      "9500220101262": 24613,
      "3500220101261": 17579051,
      "9500220101263": 31535
    },
    "related": []
  }
}